pyCensus/__init__.py
pyCensus/censusdata.py
pyCensus/endpoints.py
pyCensus/search.py
pyCensus-0.0.2.dist-info/LICENSE.txt
pyCensus-0.0.2.dist-info/METADATA
pyCensus-0.0.2.dist-info/WHEEL
pyCensus-0.0.2.dist-info/entry_points.txt
pyCensus-0.0.2.dist-info/top_level.txt
pyCensus-0.0.2.dist-info/RECORD
