Metadata-Version: 2.1
Name: pyCensus
Version: 0.0.2
Summary: A Python library to parse and data from the US Census API
Home-page: https://github.com/a-finocchiaro/pyCensus
Author: Aaron Finocchiaro
Author-email: afinny10@gmail.com
License: UNKNOWN
Download-URL: https://github.com/a-finocchiaro/pyCensus/archive/refs/tags/v_001.tar.gz
Keywords: Pandas,Census,Bureau
Platform: UNKNOWN
Classifier: Programming Language :: Python :: 3
Classifier: License :: OSI Approved :: MIT License
Classifier: Operating System :: OS Independent
Requires-Python: >=3.7
License-File: LICENSE.txt
Requires-Dist: pandas
Requires-Dist: requests
